odoo/addons/sale_timesheet_line_exclude/README.rst
odoo/addons/sale_timesheet_line_exclude/__init__.py
odoo/addons/sale_timesheet_line_exclude/__manifest__.py
odoo/addons/sale_timesheet_line_exclude/i18n/de.po
odoo/addons/sale_timesheet_line_exclude/i18n/es.po
odoo/addons/sale_timesheet_line_exclude/i18n/fr.po
odoo/addons/sale_timesheet_line_exclude/i18n/it.po
odoo/addons/sale_timesheet_line_exclude/i18n/sale_timesheet_line_exclude.pot
odoo/addons/sale_timesheet_line_exclude/models/__init__.py
odoo/addons/sale_timesheet_line_exclude/models/account_analytic_line.py
odoo/addons/sale_timesheet_line_exclude/readme/CONTRIBUTORS.rst
odoo/addons/sale_timesheet_line_exclude/readme/DESCRIPTION.rst
odoo/addons/sale_timesheet_line_exclude/readme/USAGE.rst
odoo/addons/sale_timesheet_line_exclude/static/description/icon.png
odoo/addons/sale_timesheet_line_exclude/static/description/index.html
odoo/addons/sale_timesheet_line_exclude/tests/__init__.py
odoo/addons/sale_timesheet_line_exclude/tests/test_sale_timesheet_line_exclude.py
odoo/addons/sale_timesheet_line_exclude/views/account_analytic_line.xml
odoo/addons/sale_timesheet_line_exclude/views/project_task.xml
odoo12_addon_sale_timesheet_line_exclude-12.0.1.0.0.99.dev26.dist-info/METADATA
odoo12_addon_sale_timesheet_line_exclude-12.0.1.0.0.99.dev26.dist-info/WHEEL
odoo12_addon_sale_timesheet_line_exclude-12.0.1.0.0.99.dev26.dist-info/top_level.txt
odoo12_addon_sale_timesheet_line_exclude-12.0.1.0.0.99.dev26.dist-info/RECORD
